rameau-0.2.1.dist-info/METADATA
rameau-0.2.1.dist-info/WHEEL
rameau-0.2.1.dist-info/entry_points.txt
rameau-0.2.1.dist-info/COPYING
rameau/wrapper/cwrapper.cp310-win_amd64.pyd
rameau/wrapper/__init__.py
rameau/utils/__init__.py
rameau/utils/eros_reader.py
rameau/utils/gardenia_converter.py
rameau/utils/gardenia_converters/gardenia+gar+v8.8-to-rameau.csv
rameau/utils/gardenia_converters/gardenia+rga+v8.8-to-rameau.csv
rameau/core/forecast/__init__.py
rameau/core/forecast/forecast_parameter.py
rameau/core/forecast/forecast_correction.py
rameau/core/groundwater/__init__.py
rameau/core/groundwater/groundwater.py
rameau/core/groundwater/groundwater_reservoir.py
rameau/core/groundwater/storage.py
rameau/core/inputs/__init__.py
rameau/core/inputs/input.py
rameau/core/inputs/input_format.py
rameau/core/inputs/input_collection.py
rameau/core/pumping/__init__.py
rameau/core/pumping/pumping.py
rameau/core/pumping/pumping_reservoir.py
rameau/core/snow/__init__.py
rameau/core/snow/degree_day.py
rameau/core/snow/snow_correction.py
rameau/core/snow/snow_reservoir.py
rameau/core/settings/__init__.py
rameau/core/settings/forecast_settings.py
rameau/core/settings/optimization_settings.py
rameau/core/settings/spinup_settings.py
rameau/core/settings/simulation_settings.py
rameau/core/settings/output_settings.py
rameau/core/states/__init__.py
rameau/core/states/states.py
rameau/core/states/states_collection.py
rameau/core/__init__.py
rameau/core/_abstract_wrapper.py
rameau/core/_descriptor.py
rameau/core/_main.py
rameau/core/_utils.py
rameau/core/watershed.py
rameau/core/correction.py
rameau/core/files.py
rameau/core/influence.py
rameau/core/meteo.py
rameau/core/model.py
rameau/core/overflow.py
rameau/core/parameter.py
rameau/core/progressive_reservoir.py
rameau/core/river.py
rameau/core/simulation.py
rameau/core/thornthwaite_reservoir.py
rameau/core/transfer_reservoir.py
rameau/core/tree.py
rameau/__init__.py
rameau/_typing.py
rameau/version.py
rameau-0.2.1.dist-info/RECORD
