Metadata-Version: 2.1
Name: rameau
Version: 0.2.1
Summary: Hydrological and transport modelling software developed at the French Geological Survey (BRGM)
Author: French Geological Survey
Maintainer-Email: Vergnes Jean-Pierre <jp.vergnes@brgm.fr>, Hallouin Thibault <t.hallouin@brgm.fr>
License:                     GNU GENERAL PUBLIC LICENSE
Classifier: License :: OSI Approved :: GNU General Public License (GPL)
Classifier: Programming Language :: Fortran
Classifier: Programming Language :: Python
Classifier: Programming Language :: Python :: 3
Classifier: Programming Language :: Python :: 3 :: Only
Classifier: Programming Language :: Python :: 3.8
Classifier: Programming Language :: Python :: 3.9
Classifier: Programming Language :: Python :: 3.10
Classifier: Programming Language :: Python :: 3.11
Classifier: Programming Language :: Python :: 3.12
Classifier: Programming Language :: Python :: 3.13
Classifier: Topic :: Scientific/Engineering :: Hydrology
Classifier: Intended Audience :: Science/Research
Classifier: Operating System :: Microsoft :: Windows
Classifier: Operating System :: POSIX :: Linux
Classifier: Operating System :: Unix
Project-URL: documentation, https://rameau.readthedocs.io/
Project-URL: repository, https://gitlab.com/brgm/hydrogeological-modelling/rameau
Requires-Python: >=3.8
Requires-Dist: pandas>=2.0.0
Provides-Extra: test
Requires-Dist: pytest; extra == "test"
Requires-Dist: pytest-subtests; extra == "test"
Requires-Dist: tomlkit; extra == "test"
Provides-Extra: build
Requires-Dist: spin; extra == "build"
Provides-Extra: doc
Requires-Dist: sphinx; extra == "doc"
Requires-Dist: pydata-sphinx-theme; extra == "doc"
Requires-Dist: sphinxcontrib-bibtex; extra == "doc"
Requires-Dist: myst_nb; extra == "doc"
Requires-Dist: sphinx_design; extra == "doc"
Requires-Dist: matplotlib; extra == "doc"
